setux/cli/__init__.py
setux/cli/main.py
setux/cli/usage.py
setux/cli/usage.tpl
setux/cmd/__init__.py
setux/cmd/action.py
setux/cmd/cmd.py
setux/cmd/deploy.py
setux/cmd/manage.py
setux/cmd/method.py
setux/cmd/target.py
setux/commands/actions.py
setux/commands/commands.py
setux/commands/config.py
setux/commands/doc.py
setux/commands/edit.py
setux/commands/help.py
setux/commands/logs.py
setux/commands/managers.py
setux/commands/mappings.py
setux/commands/modules.py
setux/commands/outlog.py
setux/commands/outrun.py
setux/commands/sh.py
setux/commands/sudo.py
setux/repl/__init__.py
setux/repl/repl.py
setux_repl-0.2507.1.dist-info/METADATA
setux_repl-0.2507.1.dist-info/WHEEL
setux_repl-0.2507.1.dist-info/entry_points.txt
setux_repl-0.2507.1.dist-info/top_level.txt
setux_repl-0.2507.1.dist-info/RECORD
